spotify_album_cards/__init__.py
spotify_album_cards/cli.py
spotify_album_cards-0.0.2.dist-info/LICENSE
spotify_album_cards-0.0.2.dist-info/METADATA
spotify_album_cards-0.0.2.dist-info/WHEEL
spotify_album_cards-0.0.2.dist-info/entry_points.txt
spotify_album_cards-0.0.2.dist-info/top_level.txt
spotify_album_cards-0.0.2.dist-info/RECORD
