Metadata-Version: 2.1
Name: spotify-album-cards
Version: 0.0.2
Summary: Create printable and scannable cards for albums on Spotify
Home-page: https://github.com/kevinschaul/spotify-album-cards
Author: Kevin Schaul
License: Apache License, Version 2.0
Project-URL: Issues, https://github.com/kevinschaul/spotify-album-cards/issues
Project-URL: CI, https://github.com/kevinschaul/spotify-album-cards/actions
Project-URL: Changelog, https://github.com/kevinschaul/spotify-album-cards/releases
Platform: UNKNOWN
Requires-Python: >=3.6
License-File: LICENSE
Requires-Dist: click
Requires-Dist: spotipy
Requires-Dist: python-dotenv
Requires-Dist: Pillow
Requires-Dist: requests
Provides-Extra: test
Requires-Dist: pytest ; extra == 'test'
